vt/utils/commons/commons/__init__.py
vt/utils/commons/commons/py.typed
vt/utils/commons/commons/collections/__init__.py
vt/utils/commons/commons/collections/utils.py
vt/utils/commons/commons/core_py/__init__.py
vt/utils/commons/commons/core_py/base.py
vt/utils/commons/commons/core_py/utils.py
vt/utils/commons/commons/op/__init__.py
vt/utils/commons/commons/op/base.py
vt/utils/commons/commons/os/__init__.py
vt/utils/commons/commons/os/_base_utils.py
vt/utils/commons/commons/os/linux.py
vt/utils/commons/commons/os/mac.py
vt/utils/commons/commons/os/posix.py
vt/utils/commons/commons/os/windows.py
vt/utils/commons/commons/state/__init__.py
vt/utils/commons/commons/state/done.py
vt_commons-0.0.1.dist-info/licenses/LICENSE
vt_commons-0.0.1.dist-info/METADATA
vt_commons-0.0.1.dist-info/WHEEL
vt_commons-0.0.1.dist-info/top_level.txt
vt_commons-0.0.1.dist-info/RECORD
