Metadata-Version: 2.4
Name: vt-commons
Version: 0.0.1
Summary: Reusable common utilities, interfaces and implementations for python projects.
Author-email: Suhas Krishna Srivastava <suhas.srivastava@vaastav.tech>
Maintainer-email: Suhas Krishna Srivastava <suhas.srivastava@vaastav.tech>
License-Expression: Apache-2.0
Project-URL: homepage, https://github.com/Vaastav-Technologies/py-commons
Project-URL: source, https://github.com/Vaastav-Technologies/py-commons
Project-URL: issues, https://github.com/Vaastav-Technologies/py-commons/issues
Classifier: Development Status :: 1 - Planning
Classifier: Intended Audience :: Developers
Classifier: Intended Audience :: Education
Classifier: Topic :: Education
Classifier: Topic :: Software Development :: Libraries
Classifier: Topic :: Software Development :: Libraries :: Python Modules
Classifier: Topic :: Utilities
Classifier: Programming Language :: Python :: 3.12
Classifier: Programming Language :: Python :: 3.13
Classifier: Programming Language :: Python :: 3.14
Classifier: Programming Language :: Python :: 3.15
Classifier: Programming Language :: Python :: 3 :: Only
Classifier: Typing :: Typed
Requires-Python: >=3.12
License-File: LICENSE
Dynamic: license-file
